pybliss/__init__.pyi
pybliss/pybliss_ext.abi3.so
pybliss/__init__.py
pybliss/utils.py
pybliss/py.typed
pybliss-2025.3.dist-info/RECORD
pybliss-2025.3.dist-info/WHEEL
pybliss-2025.3.dist-info/METADATA
pybliss-2025.3.dist-info/licenses/LICENSE_LGPLv3.txt
pybliss-2025.3.dist-info/licenses/LICENSE_GPLv3.txt
