Metadata-Version: 2.1
Name: pybliss
Version: 2025.3
Summary: Python wrappers around bliss graph canonicalization toolkit.
Author-Email: Kaushik Kulkarni <kaushikcfd@gmail.com>
License:                     GNU GENERAL PUBLIC LICENSE
Classifier: License :: OSI Approved :: GNU General Public License v3 (GPLv3)
Classifier: License :: OSI Approved :: GNU Lesser General Public License v3 (LGPLv3)
Classifier: Topic :: Scientific/Engineering
Classifier: Topic :: Scientific/Engineering :: Information Analysis
Classifier: Topic :: Scientific/Engineering :: Mathematics
Classifier: Topic :: Scientific/Engineering :: Visualization
Classifier: Topic :: Software Development :: Libraries
Classifier: Topic :: Utilities
Project-URL: Homepage, https://github.com/kaushikcfd/pybliss
Requires-Python: >=3.8
Requires-Dist: numpy>=1.19
Requires-Dist: pytools>=2024.0
Requires-Dist: typing_extensions>=4.0.0
